wbcompliance/__init__.py
wbcompliance/apps.py
wbcompliance/permissions.py
wbcompliance/tasks.py
wbcompliance/urls.py
wbcompliance/admin/__init__.py
wbcompliance/admin/compliance_form.py
wbcompliance/admin/compliance_task.py
wbcompliance/admin/compliance_type.py
wbcompliance/admin/utils.py
wbcompliance/admin/risk_management/__init__.py
wbcompliance/admin/risk_management/checks.py
wbcompliance/admin/risk_management/incidents.py
wbcompliance/admin/risk_management/rules.py
wbcompliance/factories/__init__.py
wbcompliance/factories/compliance.py
wbcompliance/factories/risk_management/__init__.py
wbcompliance/factories/risk_management/backends.py
wbcompliance/factories/risk_management/checks.py
wbcompliance/factories/risk_management/incidents.py
wbcompliance/factories/risk_management/rules.py
wbcompliance/filters/__init__.py
wbcompliance/filters/compliances.py
wbcompliance/filters/risk_management/__init__.py
wbcompliance/filters/risk_management/checks.py
wbcompliance/filters/risk_management/incidents.py
wbcompliance/filters/risk_management/rules.py
wbcompliance/filters/risk_management/tables.py
wbcompliance/filters/risk_management/utils.py
wbcompliance/fixtures/compliance.yaml
wbcompliance/locale/de/LC_MESSAGES/django.po
wbcompliance/locale/fr/LC_MESSAGES/django.po
wbcompliance/management/__init__.py
wbcompliance/migrations/0001_initial_squashed_squashed_0010_alter_checkedobjectincidentrelationship_resolved_by_and_more.py
wbcompliance/migrations/0011_alter_riskrule_parameters.py
wbcompliance/migrations/0012_alter_compliancetype_options.py
wbcompliance/migrations/0013_alter_riskrule_unique_together.py
wbcompliance/migrations/0014_alter_reviewcompliancetask_year.py
wbcompliance/migrations/0015_auto_20240103_0957.py
wbcompliance/migrations/0016_checkedobjectincidentrelationship_report_details_and_more.py
wbcompliance/migrations/0017_alter_rulebackend_incident_report_template.py
wbcompliance/migrations/0018_alter_rulecheckedobjectrelationship_unique_together.py
wbcompliance-2.2.6.dist-info/METADATA
wbcompliance-2.2.6.dist-info/WHEEL
wbcompliance-2.2.6.dist-info/RECORD
