Metadata-Version: 2.4
Name: wbcompliance
Version: 2.2.6
Summary: A workbench module for managing compliance.
Author-email: Christopher Wittlinger <c.wittlinger@stainly.com>
Requires-Dist: wbcore
Requires-Dist: weasyprint==57.*
